openssl_psk/__init__.py
openssl_psk/_psk.py
pyopenssl_psk-1.0.0.dist-info/LICENSE
pyopenssl_psk-1.0.0.dist-info/METADATA
pyopenssl_psk-1.0.0.dist-info/WHEEL
pyopenssl_psk-1.0.0.dist-info/top_level.txt
pyopenssl_psk-1.0.0.dist-info/RECORD
