Metadata-Version: 2.1
Name: pyopenssl-psk
Version: 1.0.0
Summary: Add PSK support to pyOpenSSL
Home-page: https://github.com/gesslerpd/pyopenssl-psk
Author: gesslerpd
Author-email: gesslerpd@users.noreply.github.com
License: Apache-2.0
Keywords: pyopenssl openssl psk
Platform: UNKNOWN
Classifier: Development Status :: 4 - Beta
Classifier: Intended Audience :: Developers
Classifier: License :: OSI Approved :: Apache Software License
Classifier: Programming Language :: Python :: 2
Classifier: Programming Language :: Python :: 2.7
Classifier: Programming Language :: Python :: 3
Classifier: Programming Language :: Python :: 3.5
Classifier: Programming Language :: Python :: 3.6
Classifier: Programming Language :: Python :: 3.7
Classifier: Programming Language :: Python :: 3.8
Requires-Dist: pyOpenSSL
Requires-Dist: cryptography (>2.2.2)
